<?xml version="1.0" encoding="utf-8"?>
<search>
  
  
  
  <entry>
    <title>Hello World</title>
    <link href="/2021/09/10/hello-world/"/>
    <url>/2021/09/10/hello-world/</url>
    
    <content type="html"><![CDATA[<p>欢迎来到我的博客。</p><p>这是我的第一个博客文章，以后将在这记录我奇奇怪怪的想法和一些迷幻的项目。</p><p>Make civil engineering better！</p><blockquote><p>一个希望用科技改变土木的<del>少</del>中年</p></blockquote>]]></content>
    
    
    <categories>
      
      <category>随手记</category>
      
    </categories>
    
    
    <tags>
      
      <tag>helloworld</tag>
      
    </tags>
    
  </entry>
  
  
  
  
</search>
